publicmodel/__init__.py
publicmodel/comm_draw.py
publicmodel/comm_music.py
publicmodel/common.py
publicmodel/countdown.py
publicmodel/test.py
publicmodel/test_common.py
publicmodel/test_common2.py
publicmodel/test_common3.py
publicmodel/test_common4.py
publicmodel/test_common5.py
publicmodel/abnormal/__init__.py
publicmodel/abnormal/error_class.py
publicmodel/img/__init__.py
publicmodel/text/__init__.py
publicmodel-3.7.8.dist-info/licenses/LICENSE
publicmodel-3.7.8.dist-info/METADATA
publicmodel-3.7.8.dist-info/WHEEL
publicmodel-3.7.8.dist-info/top_level.txt
publicmodel-3.7.8.dist-info/RECORD
