Metadata-Version: 2.4
Name: publicmodel
Version: 3.7.8
Summary: 作者: YanXinle
Home-page: https://github.com/Yanxinle1123/LeleComm
Author: YanXinle
Author-email: 1020121123@qq.com
License-File: LICENSE
Requires-Dist: qrcode~=8.2
Requires-Dist: pillow~=11.3.0
Requires-Dist: colored~=2.3.1
Requires-Dist: opencv-python~=4.12.0.88
Requires-Dist: requests~=2.32.4
Requires-Dist: bs4~=0.0.2
Requires-Dist: beautifulsoup4~=4.13.4
Requires-Dist: googletrans~=4.0.2
Requires-Dist: pytest~=8.4.1
Dynamic: author
Dynamic: author-email
Dynamic: home-page
Dynamic: license-file
Dynamic: requires-dist
Dynamic: summary
